BCO/__init__.py
BCO/download_ftp.py
BCO/ftp_settings.ini
BCO/settings.ini
BCO/settings.py
BCO/Instruments/Ceilometer.py
BCO/Instruments/Device_module.py
BCO/Instruments/Radar.py
BCO/Instruments/Radiation.py
BCO/Instruments/Raw_Instrument_Sceleton.py
BCO/Instruments/SfcWeather.py
BCO/Instruments/Windlidar.py
BCO/Instruments/__init__.py
BCO/Instruments/settings.ini
BCO/Quicklooks/RadarLidarVelocities.py
BCO/Quicklooks/Reprocess.py
BCO/Quicklooks/__init__.py
BCO/_tests/Classtests.py
BCO/_tests/Functiontests.py
BCO/_tests/__init__.py
BCO/_tests/runAll.py
BCO/tools/MRR__CIMH__LWC__60s_100m__20180520.nc
BCO/tools/__init__.py
BCO/tools/_create_dummy_nc_files.py
BCO/tools/convert.py
BCO/tools/dummy_nc_file.nc
BCO/tools/dummy_nc_file_netcdf3.nc
BCO/tools/dummy_nc_file_netcdf4.nc
BCO/tools/tools.py
BCO-1.2.7.dist-info/LICENSE
BCO-1.2.7.dist-info/METADATA
BCO-1.2.7.dist-info/WHEEL
BCO-1.2.7.dist-info/top_level.txt
BCO-1.2.7.dist-info/RECORD
