Metadata-Version: 2.1
Name: BCO
Version: 1.2.7
Summary: Python Interface to the Max-Planck-Institute Barbados Cloud Observatory data.
Home-page: https://github.com/tmachnitzki/BCO/
Author: Tobias Machnitzki
Author-email: tobias.machnitzki@mpimet.mpg.de
License: UNKNOWN
Project-URL: Documentation, http://bcoweb.mpimet.mpg.de/systems/BCO_python_doc/index.html
Project-URL: BCO Blog, https://barbados.mpimet.mpg.de/
Project-URL: Development, https://github.com/tmachnitzki/BCO
Platform: UNKNOWN
Classifier: Development Status :: 3 - Alpha
Classifier: Intended Audience :: Science/Research
Classifier: Topic :: Scientific/Engineering :: Atmospheric Science
Classifier: Programming Language :: Python :: 2
Classifier: Programming Language :: Python :: 2.7
Classifier: Programming Language :: Python :: 3
Classifier: Programming Language :: Python :: 3.5
Classifier: Programming Language :: Python :: 3.6
Classifier: License :: OSI Approved :: GNU General Public License v2 (GPLv2)
Requires-Dist: numpy (>=1.6)
Requires-Dist: matplotlib (>=1.4)
Requires-Dist: future (>=0.15.0)
Requires-Dist: scipy (>=0.19.1)
Requires-Dist: netCDF4 (>=1.1.1)
Requires-Dist: configparser (>3)
Requires-Dist: pytz
